setup.py
simplyhosting/__init__.py
simplyhosting/client.py
simplyhosting/response.py
simplyhosting/version.py
simplyhosting_api_client.egg-info/PKG-INFO
simplyhosting_api_client.egg-info/SOURCES.txt
simplyhosting_api_client.egg-info/dependency_links.txt
simplyhosting_api_client.egg-info/requires.txt
simplyhosting_api_client.egg-info/top_level.txt
test/test_client.py