Metadata-Version: 1.1
Name: simplyhosting-api-client
Version: 0.2.0
Summary: Simply Hosting API client library for Python
Home-page: https://github.com/bernardosilva/simplyhosting-api-client-python/
Author: Bernardo Vieira da Silva
Author-email: benny.stuff@gmail.com
License: MIT
Keywords: Simply Hosting,API,Client
Platform: UNKNOWN
Classifier: Programming Language :: Python :: 2.7
Classifier: Programming Language :: Python :: 3.3
Classifier: Programming Language :: Python :: 3.4
